<?xml version="1.0"?>

<bison-xml-report version="3.8.2" bug-report="bug-bison@gnu.org" url="https://www.gnu.org/software/bison/">

  <filename>parser.y</filename>

  <grammar>
    <rules>
      <rule number="0" usefulness="useful">
        <lhs>$accept</lhs>
        <rhs>
          <symbol>Program</symbol>
          <symbol>$end</symbol>
        </rhs>
      </rule>
      <rule number="1" usefulness="useful">
        <lhs>Program</lhs>
        <rhs>
          <symbol>FuncDeclList</symbol>
        </rhs>
      </rule>
      <rule number="2" usefulness="useful">
        <lhs>Program</lhs>
        <rhs>
          <symbol>Program</symbol>
          <symbol>FuncDeclList</symbol>
        </rhs>
      </rule>
      <rule number="3" usefulness="useful">
        <lhs>FuncDeclList</lhs>
        <rhs>
          <symbol>FuncDecl</symbol>
        </rhs>
      </rule>
      <rule number="4" usefulness="useful">
        <lhs>FuncDeclList</lhs>
        <rhs>
          <symbol>FuncDecl</symbol>
          <symbol>FuncDeclList</symbol>
        </rhs>
      </rule>
      <rule number="5" usefulness="useful">
        <lhs>FuncDecl</lhs>
        <rhs>
          <symbol>Type</symbol>
          <symbol>ID</symbol>
          <symbol>LPAR</symbol>
          <symbol>ParamDeclList</symbol>
          <symbol>RPAR</symbol>
          <symbol>Block</symbol>
        </rhs>
      </rule>
      <rule number="6" usefulness="useful">
        <lhs>ParamDeclList</lhs>
        <rhs>
          <empty/>
        </rhs>
      </rule>
      <rule number="7" usefulness="useful">
        <lhs>ParamDeclList</lhs>
        <rhs>
          <symbol>ParamDecl</symbol>
        </rhs>
      </rule>
      <rule number="8" usefulness="useful">
        <lhs>ParamDeclList</lhs>
        <rhs>
          <symbol>ParamDecl</symbol>
          <symbol>COMMA</symbol>
          <symbol>ParamDeclList</symbol>
        </rhs>
      </rule>
      <rule number="9" usefulness="useful">
        <lhs>Block</lhs>
        <rhs>
          <symbol>LCBRA</symbol>
          <symbol>BlockList</symbol>
          <symbol>RCBRA</symbol>
        </rhs>
      </rule>
      <rule number="10" usefulness="useful">
        <lhs>Condition</lhs>
        <rhs>
          <symbol>Expr</symbol>
          <symbol>LESSTHN</symbol>
          <symbol>Expr</symbol>
        </rhs>
      </rule>
      <rule number="11" usefulness="useful">
        <lhs>Condition</lhs>
        <rhs>
          <symbol>Expr</symbol>
          <symbol>GRTRTHN</symbol>
          <symbol>Expr</symbol>
        </rhs>
      </rule>
      <rule number="12" usefulness="useful">
        <lhs>Condition</lhs>
        <rhs>
          <symbol>Expr</symbol>
          <symbol>LESSTHNEQ</symbol>
          <symbol>Expr</symbol>
        </rhs>
      </rule>
      <rule number="13" usefulness="useful">
        <lhs>Condition</lhs>
        <rhs>
          <symbol>Expr</symbol>
          <symbol>GRTRTHNEQ</symbol>
          <symbol>Expr</symbol>
        </rhs>
      </rule>
      <rule number="14" usefulness="useful">
        <lhs>Condition</lhs>
        <rhs>
          <symbol>Expr</symbol>
          <symbol>EQEQ</symbol>
          <symbol>Expr</symbol>
        </rhs>
      </rule>
      <rule number="15" usefulness="useful">
        <lhs>Condition</lhs>
        <rhs>
          <symbol>Expr</symbol>
          <symbol>NOTEQ</symbol>
          <symbol>Expr</symbol>
        </rhs>
      </rule>
      <rule number="16" usefulness="useful">
        <lhs>BlockList</lhs>
        <rhs>
          <empty/>
        </rhs>
      </rule>
      <rule number="17" usefulness="useful">
        <lhs>BlockList</lhs>
        <rhs>
          <symbol>BlockList</symbol>
          <symbol>StmtList</symbol>
        </rhs>
      </rule>
      <rule number="18" usefulness="useful">
        <lhs>BlockList</lhs>
        <rhs>
          <symbol>BlockList</symbol>
          <symbol>VarDecl</symbol>
        </rhs>
      </rule>
      <rule number="19" usefulness="useful">
        <lhs>ParamDecl</lhs>
        <rhs>
          <symbol>Type</symbol>
          <symbol>ID</symbol>
        </rhs>
      </rule>
      <rule number="20" usefulness="useful">
        <lhs>ParamDecl</lhs>
        <rhs>
          <symbol>Type</symbol>
          <symbol>ID</symbol>
          <symbol>LBRA</symbol>
          <symbol>NUMBER</symbol>
          <symbol>RBRA</symbol>
        </rhs>
      </rule>
      <rule number="21" usefulness="useful">
        <lhs>VarDecl</lhs>
        <rhs>
          <symbol>Type</symbol>
          <symbol>ID</symbol>
          <symbol>SEMICOLON</symbol>
        </rhs>
      </rule>
      <rule number="22" usefulness="useful">
        <lhs>VarDecl</lhs>
        <rhs>
          <symbol>Type</symbol>
          <symbol>ID</symbol>
          <symbol>LBRA</symbol>
          <symbol>NUMBER</symbol>
          <symbol>RBRA</symbol>
          <symbol>SEMICOLON</symbol>
        </rhs>
      </rule>
      <rule number="23" usefulness="useful">
        <lhs>Type</lhs>
        <rhs>
          <symbol>INT</symbol>
        </rhs>
      </rule>
      <rule number="24" usefulness="useful">
        <lhs>Type</lhs>
        <rhs>
          <symbol>CHAR</symbol>
        </rhs>
      </rule>
      <rule number="25" usefulness="useful">
        <lhs>StmtList</lhs>
        <rhs>
          <symbol>Stmt</symbol>
        </rhs>
      </rule>
      <rule number="26" usefulness="useful">
        <lhs>StmtList</lhs>
        <rhs>
          <symbol>Stmt</symbol>
          <symbol>StmtList</symbol>
        </rhs>
      </rule>
      <rule number="27" usefulness="useful">
        <lhs>Stmt</lhs>
        <rhs>
          <symbol>SEMICOLON</symbol>
        </rhs>
      </rule>
      <rule number="28" usefulness="useful">
        <lhs>Stmt</lhs>
        <rhs>
          <symbol>Primary</symbol>
          <symbol>EQ</symbol>
          <symbol>Expr</symbol>
          <symbol>SEMICOLON</symbol>
        </rhs>
      </rule>
      <rule number="29" usefulness="useful">
        <lhs>Stmt</lhs>
        <rhs>
          <symbol>WRITE</symbol>
          <symbol>Expr</symbol>
          <symbol>SEMICOLON</symbol>
        </rhs>
      </rule>
      <rule number="30" usefulness="useful">
        <lhs>Stmt</lhs>
        <rhs>
          <symbol>RETURN</symbol>
          <symbol>Expr</symbol>
          <symbol>SEMICOLON</symbol>
        </rhs>
      </rule>
      <rule number="31" usefulness="useful">
        <lhs>Stmt</lhs>
        <rhs>
          <symbol>WRITELN</symbol>
          <symbol>SEMICOLON</symbol>
        </rhs>
      </rule>
      <rule number="32" usefulness="useful">
        <lhs>Stmt</lhs>
        <rhs>
          <symbol>IF</symbol>
          <symbol>LPAR</symbol>
          <symbol>Condition</symbol>
          <symbol>RPAR</symbol>
          <symbol>IfBlock</symbol>
        </rhs>
      </rule>
      <rule number="33" usefulness="useful">
        <lhs>Expr</lhs>
        <rhs>
          <symbol>Primary</symbol>
        </rhs>
      </rule>
      <rule number="34" usefulness="useful">
        <lhs>Expr</lhs>
        <rhs>
          <symbol>ID</symbol>
        </rhs>
      </rule>
      <rule number="35" usefulness="useful">
        <lhs>Expr</lhs>
        <rhs>
          <symbol>Expr</symbol>
          <symbol>MULT</symbol>
          <symbol>Expr</symbol>
        </rhs>
      </rule>
      <rule number="36" usefulness="useless-in-parser">
        <lhs>Expr</lhs>
        <rhs>
          <symbol>Expr</symbol>
          <symbol>MULT</symbol>
          <symbol>Primary</symbol>
        </rhs>
      </rule>
      <rule number="37" usefulness="useful">
        <lhs>Expr</lhs>
        <rhs>
          <symbol>Expr</symbol>
          <symbol>PLUS</symbol>
          <symbol>Expr</symbol>
        </rhs>
      </rule>
      <rule number="38" usefulness="useful">
        <lhs>Expr</lhs>
        <rhs>
          <symbol>Primary</symbol>
          <symbol>PLUS</symbol>
          <symbol>Expr</symbol>
        </rhs>
      </rule>
      <rule number="39" usefulness="useless-in-parser">
        <lhs>Expr</lhs>
        <rhs>
          <symbol>Primary</symbol>
          <symbol>PLUS</symbol>
          <symbol>Primary</symbol>
        </rhs>
      </rule>
      <rule number="40" usefulness="useful">
        <lhs>Expr</lhs>
        <rhs>
          <symbol>Primary</symbol>
          <symbol>DIV</symbol>
          <symbol>Expr</symbol>
        </rhs>
      </rule>
      <rule number="41" usefulness="useless-in-parser">
        <lhs>Expr</lhs>
        <rhs>
          <symbol>Primary</symbol>
          <symbol>DIV</symbol>
          <symbol>Primary</symbol>
        </rhs>
      </rule>
      <rule number="42" usefulness="useful">
        <lhs>Expr</lhs>
        <rhs>
          <symbol>Primary</symbol>
          <symbol>MINUS</symbol>
          <symbol>Expr</symbol>
        </rhs>
      </rule>
      <rule number="43" usefulness="useless-in-parser">
        <lhs>Expr</lhs>
        <rhs>
          <symbol>Primary</symbol>
          <symbol>MINUS</symbol>
          <symbol>Primary</symbol>
        </rhs>
      </rule>
      <rule number="44" usefulness="useful">
        <lhs>IfBlock</lhs>
        <rhs>
          <symbol>Block</symbol>
        </rhs>
      </rule>
      <rule number="45" usefulness="useful">
        <lhs>IfBlock</lhs>
        <rhs>
          <symbol>Block</symbol>
          <symbol>ELSE</symbol>
          <symbol>Block</symbol>
        </rhs>
      </rule>
      <rule number="46" usefulness="useful">
        <lhs>Primary</lhs>
        <rhs>
          <symbol>ID</symbol>
        </rhs>
      </rule>
      <rule number="47" usefulness="useful">
        <lhs>Primary</lhs>
        <rhs>
          <symbol>NUMBER</symbol>
        </rhs>
      </rule>
      <rule number="48" usefulness="useful">
        <lhs>Primary</lhs>
        <rhs>
          <symbol>ID</symbol>
          <symbol>LPAR</symbol>
          <symbol>ExprList</symbol>
          <symbol>RPAR</symbol>
        </rhs>
      </rule>
      <rule number="49" usefulness="useful">
        <lhs>Primary</lhs>
        <rhs>
          <symbol>ID</symbol>
          <symbol>LBRA</symbol>
          <symbol>NUMBER</symbol>
          <symbol>RBRA</symbol>
        </rhs>
      </rule>
      <rule number="50" usefulness="useful">
        <lhs>ExprList</lhs>
        <rhs>
          <empty/>
        </rhs>
      </rule>
      <rule number="51" usefulness="useful">
        <lhs>ExprList</lhs>
        <rhs>
          <symbol>Expr</symbol>
        </rhs>
      </rule>
      <rule number="52" usefulness="useful">
        <lhs>ExprList</lhs>
        <rhs>
          <symbol>Expr</symbol>
          <symbol>COMMA</symbol>
          <symbol>ExprList</symbol>
        </rhs>
      </rule>
      <rule number="53" usefulness="useless-in-grammar">
        <lhs>LogicOp</lhs>
        <rhs>
          <symbol>LESSTHN</symbol>
        </rhs>
      </rule>
      <rule number="54" usefulness="useless-in-grammar">
        <lhs>LogicOp</lhs>
        <rhs>
          <symbol>GRTRTHN</symbol>
        </rhs>
      </rule>
      <rule number="55" usefulness="useless-in-grammar">
        <lhs>LogicOp</lhs>
        <rhs>
          <symbol>LESSTHNEQ</symbol>
        </rhs>
      </rule>
      <rule number="56" usefulness="useless-in-grammar">
        <lhs>LogicOp</lhs>
        <rhs>
          <symbol>GRTRTHNEQ</symbol>
        </rhs>
      </rule>
      <rule number="57" usefulness="useless-in-grammar">
        <lhs>LogicOp</lhs>
        <rhs>
          <symbol>EQEQ</symbol>
        </rhs>
      </rule>
      <rule number="58" usefulness="useless-in-grammar">
        <lhs>LogicOp</lhs>
        <rhs>
          <symbol>NOTEQ</symbol>
        </rhs>
      </rule>
      <rule number="59" usefulness="useless-in-grammar">
        <lhs>DeclList</lhs>
        <rhs>
          <symbol>Decl</symbol>
          <symbol>DeclList</symbol>
        </rhs>
      </rule>
      <rule number="60" usefulness="useless-in-grammar">
        <lhs>DeclList</lhs>
        <rhs>
          <symbol>Decl</symbol>
        </rhs>
      </rule>
      <rule number="61" usefulness="useless-in-grammar">
        <lhs>DeclList</lhs>
        <rhs>
          <empty/>
        </rhs>
      </rule>
      <rule number="62" usefulness="useless-in-grammar">
        <lhs>Decl</lhs>
        <rhs>
          <symbol>VarDecl</symbol>
        </rhs>
      </rule>
      <rule number="63" usefulness="useless-in-grammar">
        <lhs>Decl</lhs>
        <rhs>
          <symbol>StmtList</symbol>
        </rhs>
      </rule>
      <rule number="64" usefulness="useless-in-grammar">
        <lhs>Decl</lhs>
        <rhs>
          <symbol>Decl</symbol>
          <symbol>VarDecl</symbol>
        </rhs>
      </rule>
      <rule number="65" usefulness="useless-in-grammar">
        <lhs>Decl</lhs>
        <rhs>
          <symbol>Decl</symbol>
          <symbol>StmtList</symbol>
        </rhs>
      </rule>
      <rule number="66" usefulness="useless-in-grammar">
        <lhs>FuncID</lhs>
        <rhs>
          <symbol>ID</symbol>
          <symbol>LPAR</symbol>
        </rhs>
      </rule>
    </rules>
    <terminals>
      <terminal symbol-number="0" token-number="0" name="$end" type="" usefulness="useful"/>
      <terminal symbol-number="1" token-number="256" name="error" type="" usefulness="useful"/>
      <terminal symbol-number="3" token-number="258" name="CHAR" type="string" usefulness="useful"/>
      <terminal symbol-number="4" token-number="259" name="INT" type="string" usefulness="useful"/>
      <terminal symbol-number="5" token-number="260" name="ID" type="string" usefulness="useful"/>
      <terminal symbol-number="6" token-number="261" name="SEMICOLON" type="char" usefulness="useful"/>
      <terminal symbol-number="7" token-number="262" name="EQ" type="char" usefulness="useful" prec="6" assoc="right"/>
      <terminal symbol-number="8" token-number="263" name="NUMBER" type="number" usefulness="useful"/>
      <terminal symbol-number="9" token-number="264" name="WRITE" type="" usefulness="useful"/>
      <terminal symbol-number="10" token-number="265" name="READ" type="" usefulness="unused-in-grammar"/>
      <terminal symbol-number="11" token-number="266" name="WRITELN" type="" usefulness="useful"/>
      <terminal symbol-number="12" token-number="267" name="RETURN" type="" usefulness="useful"/>
      <terminal symbol-number="13" token-number="268" name="IF" type="" usefulness="useful"/>
      <terminal symbol-number="14" token-number="269" name="ELSE" type="" usefulness="useful"/>
      <terminal symbol-number="15" token-number="270" name="LPAR" type="" usefulness="useful"/>
      <terminal symbol-number="16" token-number="271" name="LBRA" type="" usefulness="useful"/>
      <terminal symbol-number="17" token-number="272" name="RCBRA" type="" usefulness="useful"/>
      <terminal symbol-number="18" token-number="273" name="LCBRA" type="" usefulness="useful"/>
      <terminal symbol-number="19" token-number="274" name="COMMA" type="" usefulness="useful"/>
      <terminal symbol-number="20" token-number="275" name="PLUS" type="" usefulness="useful" prec="1" assoc="left"/>
      <terminal symbol-number="21" token-number="276" name="MINUS" type="" usefulness="useful" prec="1" assoc="left"/>
      <terminal symbol-number="22" token-number="277" name="MULT" type="" usefulness="useful" prec="2" assoc="left"/>
      <terminal symbol-number="23" token-number="278" name="DIV" type="" usefulness="useful" prec="2" assoc="left"/>
      <terminal symbol-number="24" token-number="279" name="RPAR" type="" usefulness="useful" prec="3" assoc="left"/>
      <terminal symbol-number="25" token-number="280" name="RBRA" type="" usefulness="useful" prec="3" assoc="left"/>
      <terminal symbol-number="26" token-number="281" name="UNARY" type="" usefulness="unused-in-grammar" prec="4" assoc="left"/>
      <terminal symbol-number="27" token-number="282" name="LESSTHN" type="" usefulness="useful" prec="5" assoc="left"/>
      <terminal symbol-number="28" token-number="283" name="GRTRTHN" type="" usefulness="useful" prec="5" assoc="left"/>
      <terminal symbol-number="29" token-number="284" name="LESSTHNEQ" type="" usefulness="useful" prec="5" assoc="left"/>
      <terminal symbol-number="30" token-number="285" name="GRTRTHNEQ" type="" usefulness="useful" prec="5" assoc="left"/>
      <terminal symbol-number="31" token-number="286" name="EQEQ" type="" usefulness="useful" prec="5" assoc="left"/>
      <terminal symbol-number="32" token-number="287" name="NOTEQ" type="" usefulness="useful" prec="5" assoc="left"/>
    </terminals>
    <nonterminals>
      <nonterminal symbol-number="33" name="$accept" type="" usefulness="useful"/>
      <nonterminal symbol-number="34" name="Program" type="ast" usefulness="useful"/>
      <nonterminal symbol-number="35" name="FuncDeclList" type="ast" usefulness="useful"/>
      <nonterminal symbol-number="36" name="FuncDecl" type="ast" usefulness="useful"/>
      <nonterminal symbol-number="37" name="ParamDeclList" type="ast" usefulness="useful"/>
      <nonterminal symbol-number="38" name="Block" type="ast" usefulness="useful"/>
      <nonterminal symbol-number="39" name="Condition" type="ast" usefulness="useful"/>
      <nonterminal symbol-number="40" name="BlockList" type="ast" usefulness="useful"/>
      <nonterminal symbol-number="41" name="ParamDecl" type="ast" usefulness="useful"/>
      <nonterminal symbol-number="42" name="VarDecl" type="ast" usefulness="useful"/>
      <nonterminal symbol-number="43" name="Type" type="string" usefulness="useful"/>
      <nonterminal symbol-number="44" name="StmtList" type="ast" usefulness="useful"/>
      <nonterminal symbol-number="45" name="Stmt" type="ast" usefulness="useful"/>
      <nonterminal symbol-number="46" name="Expr" type="ast" usefulness="useful"/>
      <nonterminal symbol-number="47" name="IfBlock" type="ast" usefulness="useful"/>
      <nonterminal symbol-number="48" name="Primary" type="ast" usefulness="useful"/>
      <nonterminal symbol-number="49" name="ExprList" type="ast" usefulness="useful"/>
      <nonterminal symbol-number="50" name="LogicOp" type="" usefulness="useless-in-grammar"/>
      <nonterminal symbol-number="51" name="DeclList" type="ast" usefulness="useless-in-grammar"/>
      <nonterminal symbol-number="52" name="Decl" type="ast" usefulness="useless-in-grammar"/>
      <nonterminal symbol-number="53" name="FuncID" type="ast" usefulness="useless-in-grammar"/>
    </nonterminals>
  </grammar>

  <automaton>

    <state number="0">
      <itemset>
        <item rule-number="0" dot="0"/>
        <item rule-number="1" dot="0"/>
        <item rule-number="2" dot="0"/>
        <item rule-number="3" dot="0"/>
        <item rule-number="4" dot="0"/>
        <item rule-number="5" dot="0"/>
        <item rule-number="23" dot="0"/>
        <item rule-number="24" dot="0"/>
      </itemset>
      <actions>
        <transitions>
          <transition type="shift" symbol="CHAR" state="1"/>
          <transition type="shift" symbol="INT" state="2"/>
          <transition type="goto" symbol="Program" state="3"/>
          <transition type="goto" symbol="FuncDeclList" state="4"/>
          <transition type="goto" symbol="FuncDecl" state="5"/>
          <transition type="goto" symbol="Type" state="6"/>
        </transitions>
        <errors/>
        <reductions/>
      </actions>
      <solved-conflicts/>
    </state>

    <state number="1">
      <itemset>
        <item rule-number="24" dot="1"/>
      </itemset>
      <actions>
        <transitions/>
        <errors/>
        <reductions>
          <reduction symbol="$default" rule="24" enabled="true"/>
        </reductions>
      </actions>
      <solved-conflicts/>
    </state>

    <state number="2">
      <itemset>
        <item rule-number="23" dot="1"/>
      </itemset>
      <actions>
        <transitions/>
        <errors/>
        <reductions>
          <reduction symbol="$default" rule="23" enabled="true"/>
        </reductions>
      </actions>
      <solved-conflicts/>
    </state>

    <state number="3">
      <itemset>
        <item rule-number="0" dot="1"/>
        <item rule-number="2" dot="1"/>
        <item rule-number="3" dot="0"/>
        <item rule-number="4" dot="0"/>
        <item rule-number="5" dot="0"/>
        <item rule-number="23" dot="0"/>
        <item rule-number="24" dot="0"/>
      </itemset>
      <actions>
        <transitions>
          <transition type="shift" symbol="$end" state="7"/>
          <transition type="shift" symbol="CHAR" state="1"/>
          <transition type="shift" symbol="INT" state="2"/>
          <transition type="goto" symbol="FuncDeclList" state="8"/>
          <transition type="goto" symbol="FuncDecl" state="5"/>
          <transition type="goto" symbol="Type" state="6"/>
        </transitions>
        <errors/>
        <reductions/>
      </actions>
      <solved-conflicts/>
    </state>

    <state number="4">
      <itemset>
        <item rule-number="1" dot="1"/>
      </itemset>
      <actions>
        <transitions/>
        <errors/>
        <reductions>
          <reduction symbol="$default" rule="1" enabled="true"/>
        </reductions>
      </actions>
      <solved-conflicts/>
    </state>

    <state number="5">
      <itemset>
        <item rule-number="3" dot="0"/>
        <item rule-number="3" dot="1">
          <lookaheads>
            <symbol>$end</symbol>
            <symbol>CHAR</symbol>
            <symbol>INT</symbol>
          </lookaheads>
        </item>
        <item rule-number="4" dot="0"/>
        <item rule-number="4" dot="1"/>
        <item rule-number="5" dot="0"/>
        <item rule-number="23" dot="0"/>
        <item rule-number="24" dot="0"/>
      </itemset>
      <actions>
        <transitions>
          <transition type="shift" symbol="CHAR" state="1"/>
          <transition type="shift" symbol="INT" state="2"/>
          <transition type="goto" symbol="FuncDeclList" state="9"/>
          <transition type="goto" symbol="FuncDecl" state="5"/>
          <transition type="goto" symbol="Type" state="6"/>
        </transitions>
        <errors/>
        <reductions>
          <reduction symbol="CHAR" rule="3" enabled="false"/>
          <reduction symbol="INT" rule="3" enabled="false"/>
          <reduction symbol="$default" rule="3" enabled="true"/>
        </reductions>
      </actions>
      <solved-conflicts/>
    </state>

    <state number="6">
      <itemset>
        <item rule-number="5" dot="1"/>
      </itemset>
      <actions>
        <transitions>
          <transition type="shift" symbol="ID" state="10"/>
        </transitions>
        <errors/>
        <reductions/>
      </actions>
      <solved-conflicts/>
    </state>

    <state number="7">
      <itemset>
        <item rule-number="0" dot="2"/>
      </itemset>
      <actions>
        <transitions/>
        <errors/>
        <reductions>
          <reduction symbol="$default" rule="accept" enabled="true"/>
        </reductions>
      </actions>
      <solved-conflicts/>
    </state>

    <state number="8">
      <itemset>
        <item rule-number="2" dot="2"/>
      </itemset>
      <actions>
        <transitions/>
        <errors/>
        <reductions>
          <reduction symbol="$default" rule="2" enabled="true"/>
        </reductions>
      </actions>
      <solved-conflicts/>
    </state>

    <state number="9">
      <itemset>
        <item rule-number="4" dot="2"/>
      </itemset>
      <actions>
        <transitions/>
        <errors/>
        <reductions>
          <reduction symbol="$default" rule="4" enabled="true"/>
        </reductions>
      </actions>
      <solved-conflicts/>
    </state>

    <state number="10">
      <itemset>
        <item rule-number="5" dot="2"/>
      </itemset>
      <actions>
        <transitions>
          <transition type="shift" symbol="LPAR" state="11"/>
        </transitions>
        <errors/>
        <reductions/>
      </actions>
      <solved-conflicts/>
    </state>

    <state number="11">
      <itemset>
        <item rule-number="5" dot="3"/>
        <item rule-number="6" dot="0">
          <lookaheads>
            <symbol>RPAR</symbol>
          </lookaheads>
        </item>
        <item rule-number="7" dot="0"/>
        <item rule-number="8" dot="0"/>
        <item rule-number="19" dot="0"/>
        <item rule-number="20" dot="0"/>
        <item rule-number="23" dot="0"/>
        <item rule-number="24" dot="0"/>
      </itemset>
      <actions>
        <transitions>
          <transition type="shift" symbol="CHAR" state="1"/>
          <transition type="shift" symbol="INT" state="2"/>
          <transition type="goto" symbol="ParamDeclList" state="12"/>
          <transition type="goto" symbol="ParamDecl" state="13"/>
          <transition type="goto" symbol="Type" state="14"/>
        </transitions>
        <errors/>
        <reductions>
          <reduction symbol="$default" rule="6" enabled="true"/>
        </reductions>
      </actions>
      <solved-conflicts/>
    </state>

    <state number="12">
      <itemset>
        <item rule-number="5" dot="4"/>
      </itemset>
      <actions>
        <transitions>
          <transition type="shift" symbol="RPAR" state="15"/>
        </transitions>
        <errors/>
        <reductions/>
      </actions>
      <solved-conflicts/>
    </state>

    <state number="13">
      <itemset>
        <item rule-number="7" dot="1">
          <lookaheads>
            <symbol>RPAR</symbol>
          </lookaheads>
        </item>
        <item rule-number="8" dot="1"/>
      </itemset>
      <actions>
        <transitions>
          <transition type="shift" symbol="COMMA" state="16"/>
        </transitions>
        <errors/>
        <reductions>
          <reduction symbol="$default" rule="7" enabled="true"/>
        </reductions>
      </actions>
      <solved-conflicts/>
    </state>

    <state number="14">
      <itemset>
        <item rule-number="19" dot="1"/>
        <item rule-number="20" dot="1"/>
      </itemset>
      <actions>
        <transitions>
          <transition type="shift" symbol="ID" state="17"/>
        </transitions>
        <errors/>
        <reductions/>
      </actions>
      <solved-conflicts/>
    </state>

    <state number="15">
      <itemset>
        <item rule-number="5" dot="5"/>
        <item rule-number="9" dot="0"/>
      </itemset>
      <actions>
        <transitions>
          <transition type="shift" symbol="LCBRA" state="18"/>
          <transition type="goto" symbol="Block" state="19"/>
        </transitions>
        <errors/>
        <reductions/>
      </actions>
      <solved-conflicts/>
    </state>

    <state number="16">
      <itemset>
        <item rule-number="6" dot="0">
          <lookaheads>
            <symbol>RPAR</symbol>
          </lookaheads>
        </item>
        <item rule-number="7" dot="0"/>
        <item rule-number="8" dot="0"/>
        <item rule-number="8" dot="2"/>
        <item rule-number="19" dot="0"/>
        <item rule-number="20" dot="0"/>
        <item rule-number="23" dot="0"/>
        <item rule-number="24" dot="0"/>
      </itemset>
      <actions>
        <transitions>
          <transition type="shift" symbol="CHAR" state="1"/>
          <transition type="shift" symbol="INT" state="2"/>
          <transition type="goto" symbol="ParamDeclList" state="20"/>
          <transition type="goto" symbol="ParamDecl" state="13"/>
          <transition type="goto" symbol="Type" state="14"/>
        </transitions>
        <errors/>
        <reductions>
          <reduction symbol="$default" rule="6" enabled="true"/>
        </reductions>
      </actions>
      <solved-conflicts/>
    </state>

    <state number="17">
      <itemset>
        <item rule-number="19" dot="2">
          <lookaheads>
            <symbol>COMMA</symbol>
            <symbol>RPAR</symbol>
          </lookaheads>
        </item>
        <item rule-number="20" dot="2"/>
      </itemset>
      <actions>
        <transitions>
          <transition type="shift" symbol="LBRA" state="21"/>
        </transitions>
        <errors/>
        <reductions>
          <reduction symbol="$default" rule="19" enabled="true"/>
        </reductions>
      </actions>
      <solved-conflicts/>
    </state>

    <state number="18">
      <itemset>
        <item rule-number="9" dot="1"/>
        <item rule-number="16" dot="0"/>
        <item rule-number="17" dot="0"/>
        <item rule-number="18" dot="0"/>
      </itemset>
      <actions>
        <transitions>
          <transition type="goto" symbol="BlockList" state="22"/>
        </transitions>
        <errors/>
        <reductions>
          <reduction symbol="$default" rule="16" enabled="true"/>
        </reductions>
      </actions>
      <solved-conflicts/>
    </state>

    <state number="19">
      <itemset>
        <item rule-number="5" dot="6"/>
      </itemset>
      <actions>
        <transitions/>
        <errors/>
        <reductions>
          <reduction symbol="$default" rule="5" enabled="true"/>
        </reductions>
      </actions>
      <solved-conflicts/>
    </state>

    <state number="20">
      <itemset>
        <item rule-number="8" dot="3"/>
      </itemset>
      <actions>
        <transitions/>
        <errors/>
        <reductions>
          <reduction symbol="$default" rule="8" enabled="true"/>
        </reductions>
      </actions>
      <solved-conflicts/>
    </state>

    <state number="21">
      <itemset>
        <item rule-number="20" dot="3"/>
      </itemset>
      <actions>
        <transitions>
          <transition type="shift" symbol="NUMBER" state="23"/>
        </transitions>
        <errors/>
        <reductions/>
      </actions>
      <solved-conflicts/>
    </state>

    <state number="22">
      <itemset>
        <item rule-number="9" dot="2"/>
        <item rule-number="17" dot="1"/>
        <item rule-number="18" dot="1"/>
        <item rule-number="21" dot="0"/>
        <item rule-number="22" dot="0"/>
        <item rule-number="23" dot="0"/>
        <item rule-number="24" dot="0"/>
        <item rule-number="25" dot="0"/>
        <item rule-number="26" dot="0"/>
        <item rule-number="27" dot="0"/>
        <item rule-number="28" dot="0"/>
        <item rule-number="29" dot="0"/>
        <item rule-number="30" dot="0"/>
        <item rule-number="31" dot="0"/>
        <item rule-number="32" dot="0"/>
        <item rule-number="46" dot="0"/>
        <item rule-number="47" dot="0"/>
        <item rule-number="48" dot="0"/>
        <item rule-number="49" dot="0"/>
      </itemset>
      <actions>
        <transitions>
          <transition type="shift" symbol="CHAR" state="1"/>
          <transition type="shift" symbol="INT" state="2"/>
          <transition type="shift" symbol="ID" state="24"/>
          <transition type="shift" symbol="SEMICOLON" state="25"/>
          <transition type="shift" symbol="NUMBER" state="26"/>
          <transition type="shift" symbol="WRITE" state="27"/>
          <transition type="shift" symbol="WRITELN" state="28"/>
          <transition type="shift" symbol="RETURN" state="29"/>
          <transition type="shift" symbol="IF" state="30"/>
          <transition type="shift" symbol="RCBRA" state="31"/>
          <transition type="goto" symbol="VarDecl" state="32"/>
          <transition type="goto" symbol="Type" state="33"/>
          <transition type="goto" symbol="StmtList" state="34"/>
          <transition type="goto" symbol="Stmt" state="35"/>
          <transition type="goto" symbol="Primary" state="36"/>
        </transitions>
        <errors/>
        <reductions/>
      </actions>
      <solved-conflicts/>
    </state>

    <state number="23">
      <itemset>
        <item rule-number="20" dot="4"/>
      </itemset>
      <actions>
        <transitions>
          <transition type="shift" symbol="RBRA" state="37"/>
        </transitions>
        <errors/>
        <reductions/>
      </actions>
      <solved-conflicts/>
    </state>

    <state number="24">
      <itemset>
        <item rule-number="46" dot="1">
          <lookaheads>
            <symbol>EQ</symbol>
          </lookaheads>
        </item>
        <item rule-number="48" dot="1"/>
        <item rule-number="49" dot="1"/>
      </itemset>
      <actions>
        <transitions>
          <transition type="shift" symbol="LPAR" state="38"/>
          <transition type="shift" symbol="LBRA" state="39"/>
        </transitions>
        <errors/>
        <reductions>
          <reduction symbol="$default" rule="46" enabled="true"/>
        </reductions>
      </actions>
      <solved-conflicts/>
    </state>

    <state number="25">
      <itemset>
        <item rule-number="27" dot="1"/>
      </itemset>
      <actions>
        <transitions/>
        <errors/>
        <reductions>
          <reduction symbol="$default" rule="27" enabled="true"/>
        </reductions>
      </actions>
      <solved-conflicts/>
    </state>

    <state number="26">
      <itemset>
        <item rule-number="47" dot="1"/>
      </itemset>
      <actions>
        <transitions/>
        <errors/>
        <reductions>
          <reduction symbol="$default" rule="47" enabled="true"/>
        </reductions>
      </actions>
      <solved-conflicts/>
    </state>

    <state number="27">
      <itemset>
        <item rule-number="29" dot="1"/>
        <item rule-number="33" dot="0"/>
        <item rule-number="34" dot="0"/>
        <item rule-number="35" dot="0"/>
        <item rule-number="36" dot="0"/>
        <item rule-number="37" dot="0"/>
        <item rule-number="38" dot="0"/>
        <item rule-number="39" dot="0"/>
        <item rule-number="40" dot="0"/>
        <item rule-number="41" dot="0"/>
        <item rule-number="42" dot="0"/>
        <item rule-number="43" dot="0"/>
        <item rule-number="46" dot="0"/>
        <item rule-number="47" dot="0"/>
        <item rule-number="48" dot="0"/>
        <item rule-number="49" dot="0"/>
      </itemset>
      <actions>
        <transitions>
          <transition type="shift" symbol="ID" state="40"/>
          <transition type="shift" symbol="NUMBER" state="26"/>
          <transition type="goto" symbol="Expr" state="41"/>
          <transition type="goto" symbol="Primary" state="42"/>
        </transitions>
        <errors/>
        <reductions/>
      </actions>
      <solved-conflicts/>
    </state>

    <state number="28">
      <itemset>
        <item rule-number="31" dot="1"/>
      </itemset>
      <actions>
        <transitions>
          <transition type="shift" symbol="SEMICOLON" state="43"/>
        </transitions>
        <errors/>
        <reductions/>
      </actions>
      <solved-conflicts/>
    </state>

    <state number="29">
      <itemset>
        <item rule-number="30" dot="1"/>
        <item rule-number="33" dot="0"/>
        <item rule-number="34" dot="0"/>
        <item rule-number="35" dot="0"/>
        <item rule-number="36" dot="0"/>
        <item rule-number="37" dot="0"/>
        <item rule-number="38" dot="0"/>
        <item rule-number="39" dot="0"/>
        <item rule-number="40" dot="0"/>
        <item rule-number="41" dot="0"/>
        <item rule-number="42" dot="0"/>
        <item rule-number="43" dot="0"/>
        <item rule-number="46" dot="0"/>
        <item rule-number="47" dot="0"/>
        <item rule-number="48" dot="0"/>
        <item rule-number="49" dot="0"/>
      </itemset>
      <actions>
        <transitions>
          <transition type="shift" symbol="ID" state="40"/>
          <transition type="shift" symbol="NUMBER" state="26"/>
          <transition type="goto" symbol="Expr" state="44"/>
          <transition type="goto" symbol="Primary" state="42"/>
        </transitions>
        <errors/>
        <reductions/>
      </actions>
      <solved-conflicts/>
    </state>

    <state number="30">
      <itemset>
        <item rule-number="32" dot="1"/>
      </itemset>
      <actions>
        <transitions>
          <transition type="shift" symbol="LPAR" state="45"/>
        </transitions>
        <errors/>
        <reductions/>
      </actions>
      <solved-conflicts/>
    </state>

    <state number="31">
      <itemset>
        <item rule-number="9" dot="3"/>
      </itemset>
      <actions>
        <transitions/>
        <errors/>
        <reductions>
          <reduction symbol="$default" rule="9" enabled="true"/>
        </reductions>
      </actions>
      <solved-conflicts/>
    </state>

    <state number="32">
      <itemset>
        <item rule-number="18" dot="2"/>
      </itemset>
      <actions>
        <transitions/>
        <errors/>
        <reductions>
          <reduction symbol="$default" rule="18" enabled="true"/>
        </reductions>
      </actions>
      <solved-conflicts/>
    </state>

    <state number="33">
      <itemset>
        <item rule-number="21" dot="1"/>
        <item rule-number="22" dot="1"/>
      </itemset>
      <actions>
        <transitions>
          <transition type="shift" symbol="ID" state="46"/>
        </transitions>
        <errors/>
        <reductions/>
      </actions>
      <solved-conflicts/>
    </state>

    <state number="34">
      <itemset>
        <item rule-number="17" dot="2"/>
      </itemset>
      <actions>
        <transitions/>
        <errors/>
        <reductions>
          <reduction symbol="$default" rule="17" enabled="true"/>
        </reductions>
      </actions>
      <solved-conflicts/>
    </state>

    <state number="35">
      <itemset>
        <item rule-number="25" dot="0"/>
        <item rule-number="25" dot="1">
          <lookaheads>
            <symbol>CHAR</symbol>
            <symbol>INT</symbol>
            <symbol>ID</symbol>
            <symbol>SEMICOLON</symbol>
            <symbol>NUMBER</symbol>
            <symbol>WRITE</symbol>
            <symbol>WRITELN</symbol>
            <symbol>RETURN</symbol>
            <symbol>IF</symbol>
            <symbol>RCBRA</symbol>
          </lookaheads>
        </item>
        <item rule-number="26" dot="0"/>
        <item rule-number="26" dot="1"/>
        <item rule-number="27" dot="0"/>
        <item rule-number="28" dot="0"/>
        <item rule-number="29" dot="0"/>
        <item rule-number="30" dot="0"/>
        <item rule-number="31" dot="0"/>
        <item rule-number="32" dot="0"/>
        <item rule-number="46" dot="0"/>
        <item rule-number="47" dot="0"/>
        <item rule-number="48" dot="0"/>
        <item rule-number="49" dot="0"/>
      </itemset>
      <actions>
        <transitions>
          <transition type="shift" symbol="ID" state="24"/>
          <transition type="shift" symbol="SEMICOLON" state="25"/>
          <transition type="shift" symbol="NUMBER" state="26"/>
          <transition type="shift" symbol="WRITE" state="27"/>
          <transition type="shift" symbol="WRITELN" state="28"/>
          <transition type="shift" symbol="RETURN" state="29"/>
          <transition type="shift" symbol="IF" state="30"/>
          <transition type="goto" symbol="StmtList" state="47"/>
          <transition type="goto" symbol="Stmt" state="35"/>
          <transition type="goto" symbol="Primary" state="36"/>
        </transitions>
        <errors/>
        <reductions>
          <reduction symbol="ID" rule="25" enabled="false"/>
          <reduction symbol="SEMICOLON" rule="25" enabled="false"/>
          <reduction symbol="NUMBER" rule="25" enabled="false"/>
          <reduction symbol="WRITE" rule="25" enabled="false"/>
          <reduction symbol="WRITELN" rule="25" enabled="false"/>
          <reduction symbol="RETURN" rule="25" enabled="false"/>
          <reduction symbol="IF" rule="25" enabled="false"/>
          <reduction symbol="$default" rule="25" enabled="true"/>
        </reductions>
      </actions>
      <solved-conflicts/>
    </state>

    <state number="36">
      <itemset>
        <item rule-number="28" dot="1"/>
      </itemset>
      <actions>
        <transitions>
          <transition type="shift" symbol="EQ" state="48"/>
        </transitions>
        <errors/>
        <reductions/>
      </actions>
      <solved-conflicts/>
    </state>

    <state number="37">
      <itemset>
        <item rule-number="20" dot="5"/>
      </itemset>
      <actions>
        <transitions/>
        <errors/>
        <reductions>
          <reduction symbol="$default" rule="20" enabled="true"/>
        </reductions>
      </actions>
      <solved-conflicts/>
    </state>

    <state number="38">
      <itemset>
        <item rule-number="33" dot="0"/>
        <item rule-number="34" dot="0"/>
        <item rule-number="35" dot="0"/>
        <item rule-number="36" dot="0"/>
        <item rule-number="37" dot="0"/>
        <item rule-number="38" dot="0"/>
        <item rule-number="39" dot="0"/>
        <item rule-number="40" dot="0"/>
        <item rule-number="41" dot="0"/>
        <item rule-number="42" dot="0"/>
        <item rule-number="43" dot="0"/>
        <item rule-number="46" dot="0"/>
        <item rule-number="47" dot="0"/>
        <item rule-number="48" dot="0"/>
        <item rule-number="48" dot="2"/>
        <item rule-number="49" dot="0"/>
        <item rule-number="50" dot="0">
          <lookaheads>
            <symbol>RPAR</symbol>
          </lookaheads>
        </item>
        <item rule-number="51" dot="0"/>
        <item rule-number="52" dot="0"/>
      </itemset>
      <actions>
        <transitions>
          <transition type="shift" symbol="ID" state="40"/>
          <transition type="shift" symbol="NUMBER" state="26"/>
          <transition type="goto" symbol="Expr" state="49"/>
          <transition type="goto" symbol="Primary" state="42"/>
          <transition type="goto" symbol="ExprList" state="50"/>
        </transitions>
        <errors/>
        <reductions>
          <reduction symbol="$default" rule="50" enabled="true"/>
        </reductions>
      </actions>
      <solved-conflicts/>
    </state>

    <state number="39">
      <itemset>
        <item rule-number="49" dot="2"/>
      </itemset>
      <actions>
        <transitions>
          <transition type="shift" symbol="NUMBER" state="51"/>
        </transitions>
        <errors/>
        <reductions/>
      </actions>
      <solved-conflicts/>
    </state>

    <state number="40">
      <itemset>
        <item rule-number="34" dot="1">
          <lookaheads>
            <symbol>SEMICOLON</symbol>
            <symbol>COMMA</symbol>
            <symbol>PLUS</symbol>
            <symbol>MULT</symbol>
            <symbol>RPAR</symbol>
            <symbol>LESSTHN</symbol>
            <symbol>GRTRTHN</symbol>
            <symbol>LESSTHNEQ</symbol>
            <symbol>GRTRTHNEQ</symbol>
            <symbol>EQEQ</symbol>
            <symbol>NOTEQ</symbol>
          </lookaheads>
        </item>
        <item rule-number="46" dot="1">
          <lookaheads>
            <symbol>SEMICOLON</symbol>
            <symbol>COMMA</symbol>
            <symbol>PLUS</symbol>
            <symbol>MINUS</symbol>
            <symbol>MULT</symbol>
            <symbol>DIV</symbol>
            <symbol>RPAR</symbol>
            <symbol>LESSTHN</symbol>
            <symbol>GRTRTHN</symbol>
            <symbol>LESSTHNEQ</symbol>
            <symbol>GRTRTHNEQ</symbol>
            <symbol>EQEQ</symbol>
            <symbol>NOTEQ</symbol>
          </lookaheads>
        </item>
        <item rule-number="48" dot="1"/>
        <item rule-number="49" dot="1"/>
      </itemset>
      <actions>
        <transitions>
          <transition type="shift" symbol="LPAR" state="38"/>
          <transition type="shift" symbol="LBRA" state="39"/>
        </transitions>
        <errors/>
        <reductions>
          <reduction symbol="SEMICOLON" rule="34" enabled="true"/>
          <reduction symbol="SEMICOLON" rule="46" enabled="false"/>
          <reduction symbol="COMMA" rule="34" enabled="true"/>
          <reduction symbol="COMMA" rule="46" enabled="false"/>
          <reduction symbol="PLUS" rule="34" enabled="true"/>
          <reduction symbol="PLUS" rule="46" enabled="false"/>
          <reduction symbol="MINUS" rule="46" enabled="true"/>
          <reduction symbol="MULT" rule="34" enabled="true"/>
          <reduction symbol="MULT" rule="46" enabled="false"/>
          <reduction symbol="DIV" rule="46" enabled="true"/>
          <reduction symbol="RPAR" rule="34" enabled="true"/>
          <reduction symbol="RPAR" rule="46" enabled="false"/>
          <reduction symbol="LESSTHN" rule="34" enabled="true"/>
          <reduction symbol="LESSTHN" rule="46" enabled="false"/>
          <reduction symbol="GRTRTHN" rule="34" enabled="true"/>
          <reduction symbol="GRTRTHN" rule="46" enabled="false"/>
          <reduction symbol="LESSTHNEQ" rule="34" enabled="true"/>
          <reduction symbol="LESSTHNEQ" rule="46" enabled="false"/>
          <reduction symbol="GRTRTHNEQ" rule="34" enabled="true"/>
          <reduction symbol="GRTRTHNEQ" rule="46" enabled="false"/>
          <reduction symbol="EQEQ" rule="34" enabled="true"/>
          <reduction symbol="EQEQ" rule="46" enabled="false"/>
          <reduction symbol="NOTEQ" rule="34" enabled="true"/>
          <reduction symbol="NOTEQ" rule="46" enabled="false"/>
          <reduction symbol="$default" rule="34" enabled="true"/>
        </reductions>
      </actions>
      <solved-conflicts/>
    </state>

    <state number="41">
      <itemset>
        <item rule-number="29" dot="2"/>
        <item rule-number="35" dot="1"/>
        <item rule-number="36" dot="1"/>
        <item rule-number="37" dot="1"/>
      </itemset>
      <actions>
        <transitions>
          <transition type="shift" symbol="SEMICOLON" state="52"/>
          <transition type="shift" symbol="PLUS" state="53"/>
          <transition type="shift" symbol="MULT" state="54"/>
        </transitions>
        <errors/>
        <reductions/>
      </actions>
      <solved-conflicts/>
    </state>

    <state number="42">
      <itemset>
        <item rule-number="33" dot="1">
          <lookaheads>
            <symbol>SEMICOLON</symbol>
            <symbol>COMMA</symbol>
            <symbol>PLUS</symbol>
            <symbol>MULT</symbol>
            <symbol>RPAR</symbol>
            <symbol>LESSTHN</symbol>
            <symbol>GRTRTHN</symbol>
            <symbol>LESSTHNEQ</symbol>
            <symbol>GRTRTHNEQ</symbol>
            <symbol>EQEQ</symbol>
            <symbol>NOTEQ</symbol>
          </lookaheads>
        </item>
        <item rule-number="38" dot="1"/>
        <item rule-number="39" dot="1"/>
        <item rule-number="40" dot="1"/>
        <item rule-number="41" dot="1"/>
        <item rule-number="42" dot="1"/>
        <item rule-number="43" dot="1"/>
      </itemset>
      <actions>
        <transitions>
          <transition type="shift" symbol="PLUS" state="55"/>
          <transition type="shift" symbol="MINUS" state="56"/>
          <transition type="shift" symbol="DIV" state="57"/>
        </transitions>
        <errors/>
        <reductions>
          <reduction symbol="PLUS" rule="33" enabled="false"/>
          <reduction symbol="$default" rule="33" enabled="true"/>
        </reductions>
      </actions>
      <solved-conflicts/>
    </state>

    <state number="43">
      <itemset>
        <item rule-number="31" dot="2"/>
      </itemset>
      <actions>
        <transitions/>
        <errors/>
        <reductions>
          <reduction symbol="$default" rule="31" enabled="true"/>
        </reductions>
      </actions>
      <solved-conflicts/>
    </state>

    <state number="44">
      <itemset>
        <item rule-number="30" dot="2"/>
        <item rule-number="35" dot="1"/>
        <item rule-number="36" dot="1"/>
        <item rule-number="37" dot="1"/>
      </itemset>
      <actions>
        <transitions>
          <transition type="shift" symbol="SEMICOLON" state="58"/>
          <transition type="shift" symbol="PLUS" state="53"/>
          <transition type="shift" symbol="MULT" state="54"/>
        </transitions>
        <errors/>
        <reductions/>
      </actions>
      <solved-conflicts/>
    </state>

    <state number="45">
      <itemset>
        <item rule-number="10" dot="0"/>
        <item rule-number="11" dot="0"/>
        <item rule-number="12" dot="0"/>
        <item rule-number="13" dot="0"/>
        <item rule-number="14" dot="0"/>
        <item rule-number="15" dot="0"/>
        <item rule-number="32" dot="2"/>
        <item rule-number="33" dot="0"/>
        <item rule-number="34" dot="0"/>
        <item rule-number="35" dot="0"/>
        <item rule-number="36" dot="0"/>
        <item rule-number="37" dot="0"/>
        <item rule-number="38" dot="0"/>
        <item rule-number="39" dot="0"/>
        <item rule-number="40" dot="0"/>
        <item rule-number="41" dot="0"/>
        <item rule-number="42" dot="0"/>
        <item rule-number="43" dot="0"/>
        <item rule-number="46" dot="0"/>
        <item rule-number="47" dot="0"/>
        <item rule-number="48" dot="0"/>
        <item rule-number="49" dot="0"/>
      </itemset>
      <actions>
        <transitions>
          <transition type="shift" symbol="ID" state="40"/>
          <transition type="shift" symbol="NUMBER" state="26"/>
          <transition type="goto" symbol="Condition" state="59"/>
          <transition type="goto" symbol="Expr" state="60"/>
          <transition type="goto" symbol="Primary" state="42"/>
        </transitions>
        <errors/>
        <reductions/>
      </actions>
      <solved-conflicts/>
    </state>

    <state number="46">
      <itemset>
        <item rule-number="21" dot="2"/>
        <item rule-number="22" dot="2"/>
      </itemset>
      <actions>
        <transitions>
          <transition type="shift" symbol="SEMICOLON" state="61"/>
          <transition type="shift" symbol="LBRA" state="62"/>
        </transitions>
        <errors/>
        <reductions/>
      </actions>
      <solved-conflicts/>
    </state>

    <state number="47">
      <itemset>
        <item rule-number="26" dot="2"/>
      </itemset>
      <actions>
        <transitions/>
        <errors/>
        <reductions>
          <reduction symbol="$default" rule="26" enabled="true"/>
        </reductions>
      </actions>
      <solved-conflicts/>
    </state>

    <state number="48">
      <itemset>
        <item rule-number="28" dot="2"/>
        <item rule-number="33" dot="0"/>
        <item rule-number="34" dot="0"/>
        <item rule-number="35" dot="0"/>
        <item rule-number="36" dot="0"/>
        <item rule-number="37" dot="0"/>
        <item rule-number="38" dot="0"/>
        <item rule-number="39" dot="0"/>
        <item rule-number="40" dot="0"/>
        <item rule-number="41" dot="0"/>
        <item rule-number="42" dot="0"/>
        <item rule-number="43" dot="0"/>
        <item rule-number="46" dot="0"/>
        <item rule-number="47" dot="0"/>
        <item rule-number="48" dot="0"/>
        <item rule-number="49" dot="0"/>
      </itemset>
      <actions>
        <transitions>
          <transition type="shift" symbol="ID" state="40"/>
          <transition type="shift" symbol="NUMBER" state="26"/>
          <transition type="goto" symbol="Expr" state="63"/>
          <transition type="goto" symbol="Primary" state="42"/>
        </transitions>
        <errors/>
        <reductions/>
      </actions>
      <solved-conflicts/>
    </state>

    <state number="49">
      <itemset>
        <item rule-number="35" dot="1"/>
        <item rule-number="36" dot="1"/>
        <item rule-number="37" dot="1"/>
        <item rule-number="51" dot="1">
          <lookaheads>
            <symbol>RPAR</symbol>
          </lookaheads>
        </item>
        <item rule-number="52" dot="1"/>
      </itemset>
      <actions>
        <transitions>
          <transition type="shift" symbol="COMMA" state="64"/>
          <transition type="shift" symbol="PLUS" state="53"/>
          <transition type="shift" symbol="MULT" state="54"/>
        </transitions>
        <errors/>
        <reductions>
          <reduction symbol="$default" rule="51" enabled="true"/>
        </reductions>
      </actions>
      <solved-conflicts/>
    </state>

    <state number="50">
      <itemset>
        <item rule-number="48" dot="3"/>
      </itemset>
      <actions>
        <transitions>
          <transition type="shift" symbol="RPAR" state="65"/>
        </transitions>
        <errors/>
        <reductions/>
      </actions>
      <solved-conflicts/>
    </state>

    <state number="51">
      <itemset>
        <item rule-number="49" dot="3"/>
      </itemset>
      <actions>
        <transitions>
          <transition type="shift" symbol="RBRA" state="66"/>
        </transitions>
        <errors/>
        <reductions/>
      </actions>
      <solved-conflicts/>
    </state>

    <state number="52">
      <itemset>
        <item rule-number="29" dot="3"/>
      </itemset>
      <actions>
        <transitions/>
        <errors/>
        <reductions>
          <reduction symbol="$default" rule="29" enabled="true"/>
        </reductions>
      </actions>
      <solved-conflicts/>
    </state>

    <state number="53">
      <itemset>
        <item rule-number="33" dot="0"/>
        <item rule-number="34" dot="0"/>
        <item rule-number="35" dot="0"/>
        <item rule-number="36" dot="0"/>
        <item rule-number="37" dot="0"/>
        <item rule-number="37" dot="2"/>
        <item rule-number="38" dot="0"/>
        <item rule-number="39" dot="0"/>
        <item rule-number="40" dot="0"/>
        <item rule-number="41" dot="0"/>
        <item rule-number="42" dot="0"/>
        <item rule-number="43" dot="0"/>
        <item rule-number="46" dot="0"/>
        <item rule-number="47" dot="0"/>
        <item rule-number="48" dot="0"/>
        <item rule-number="49" dot="0"/>
      </itemset>
      <actions>
        <transitions>
          <transition type="shift" symbol="ID" state="40"/>
          <transition type="shift" symbol="NUMBER" state="26"/>
          <transition type="goto" symbol="Expr" state="67"/>
          <transition type="goto" symbol="Primary" state="42"/>
        </transitions>
        <errors/>
        <reductions/>
      </actions>
      <solved-conflicts/>
    </state>

    <state number="54">
      <itemset>
        <item rule-number="33" dot="0"/>
        <item rule-number="34" dot="0"/>
        <item rule-number="35" dot="0"/>
        <item rule-number="35" dot="2"/>
        <item rule-number="36" dot="0"/>
        <item rule-number="36" dot="2"/>
        <item rule-number="37" dot="0"/>
        <item rule-number="38" dot="0"/>
        <item rule-number="39" dot="0"/>
        <item rule-number="40" dot="0"/>
        <item rule-number="41" dot="0"/>
        <item rule-number="42" dot="0"/>
        <item rule-number="43" dot="0"/>
        <item rule-number="46" dot="0"/>
        <item rule-number="47" dot="0"/>
        <item rule-number="48" dot="0"/>
        <item rule-number="49" dot="0"/>
      </itemset>
      <actions>
        <transitions>
          <transition type="shift" symbol="ID" state="40"/>
          <transition type="shift" symbol="NUMBER" state="26"/>
          <transition type="goto" symbol="Expr" state="68"/>
          <transition type="goto" symbol="Primary" state="69"/>
        </transitions>
        <errors/>
        <reductions/>
      </actions>
      <solved-conflicts/>
    </state>

    <state number="55">
      <itemset>
        <item rule-number="33" dot="0"/>
        <item rule-number="34" dot="0"/>
        <item rule-number="35" dot="0"/>
        <item rule-number="36" dot="0"/>
        <item rule-number="37" dot="0"/>
        <item rule-number="38" dot="0"/>
        <item rule-number="38" dot="2"/>
        <item rule-number="39" dot="0"/>
        <item rule-number="39" dot="2"/>
        <item rule-number="40" dot="0"/>
        <item rule-number="41" dot="0"/>
        <item rule-number="42" dot="0"/>
        <item rule-number="43" dot="0"/>
        <item rule-number="46" dot="0"/>
        <item rule-number="47" dot="0"/>
        <item rule-number="48" dot="0"/>
        <item rule-number="49" dot="0"/>
      </itemset>
      <actions>
        <transitions>
          <transition type="shift" symbol="ID" state="40"/>
          <transition type="shift" symbol="NUMBER" state="26"/>
          <transition type="goto" symbol="Expr" state="70"/>
          <transition type="goto" symbol="Primary" state="71"/>
        </transitions>
        <errors/>
        <reductions/>
      </actions>
      <solved-conflicts/>
    </state>

    <state number="56">
      <itemset>
        <item rule-number="33" dot="0"/>
        <item rule-number="34" dot="0"/>
        <item rule-number="35" dot="0"/>
        <item rule-number="36" dot="0"/>
        <item rule-number="37" dot="0"/>
        <item rule-number="38" dot="0"/>
        <item rule-number="39" dot="0"/>
        <item rule-number="40" dot="0"/>
        <item rule-number="41" dot="0"/>
        <item rule-number="42" dot="0"/>
        <item rule-number="42" dot="2"/>
        <item rule-number="43" dot="0"/>
        <item rule-number="43" dot="2"/>
        <item rule-number="46" dot="0"/>
        <item rule-number="47" dot="0"/>
        <item rule-number="48" dot="0"/>
        <item rule-number="49" dot="0"/>
      </itemset>
      <actions>
        <transitions>
          <transition type="shift" symbol="ID" state="40"/>
          <transition type="shift" symbol="NUMBER" state="26"/>
          <transition type="goto" symbol="Expr" state="72"/>
          <transition type="goto" symbol="Primary" state="73"/>
        </transitions>
        <errors/>
        <reductions/>
      </actions>
      <solved-conflicts/>
    </state>

    <state number="57">
      <itemset>
        <item rule-number="33" dot="0"/>
        <item rule-number="34" dot="0"/>
        <item rule-number="35" dot="0"/>
        <item rule-number="36" dot="0"/>
        <item rule-number="37" dot="0"/>
        <item rule-number="38" dot="0"/>
        <item rule-number="39" dot="0"/>
        <item rule-number="40" dot="0"/>
        <item rule-number="40" dot="2"/>
        <item rule-number="41" dot="0"/>
        <item rule-number="41" dot="2"/>
        <item rule-number="42" dot="0"/>
        <item rule-number="43" dot="0"/>
        <item rule-number="46" dot="0"/>
        <item rule-number="47" dot="0"/>
        <item rule-number="48" dot="0"/>
        <item rule-number="49" dot="0"/>
      </itemset>
      <actions>
        <transitions>
          <transition type="shift" symbol="ID" state="40"/>
          <transition type="shift" symbol="NUMBER" state="26"/>
          <transition type="goto" symbol="Expr" state="74"/>
          <transition type="goto" symbol="Primary" state="75"/>
        </transitions>
        <errors/>
        <reductions/>
      </actions>
      <solved-conflicts/>
    </state>

    <state number="58">
      <itemset>
        <item rule-number="30" dot="3"/>
      </itemset>
      <actions>
        <transitions/>
        <errors/>
        <reductions>
          <reduction symbol="$default" rule="30" enabled="true"/>
        </reductions>
      </actions>
      <solved-conflicts/>
    </state>

    <state number="59">
      <itemset>
        <item rule-number="32" dot="3"/>
      </itemset>
      <actions>
        <transitions>
          <transition type="shift" symbol="RPAR" state="76"/>
        </transitions>
        <errors/>
        <reductions/>
      </actions>
      <solved-conflicts/>
    </state>

    <state number="60">
      <itemset>
        <item rule-number="10" dot="1"/>
        <item rule-number="11" dot="1"/>
        <item rule-number="12" dot="1"/>
        <item rule-number="13" dot="1"/>
        <item rule-number="14" dot="1"/>
        <item rule-number="15" dot="1"/>
        <item rule-number="35" dot="1"/>
        <item rule-number="36" dot="1"/>
        <item rule-number="37" dot="1"/>
      </itemset>
      <actions>
        <transitions>
          <transition type="shift" symbol="PLUS" state="53"/>
          <transition type="shift" symbol="MULT" state="54"/>
          <transition type="shift" symbol="LESSTHN" state="77"/>
          <transition type="shift" symbol="GRTRTHN" state="78"/>
          <transition type="shift" symbol="LESSTHNEQ" state="79"/>
          <transition type="shift" symbol="GRTRTHNEQ" state="80"/>
          <transition type="shift" symbol="EQEQ" state="81"/>
          <transition type="shift" symbol="NOTEQ" state="82"/>
        </transitions>
        <errors/>
        <reductions/>
      </actions>
      <solved-conflicts/>
    </state>

    <state number="61">
      <itemset>
        <item rule-number="21" dot="3"/>
      </itemset>
      <actions>
        <transitions/>
        <errors/>
        <reductions>
          <reduction symbol="$default" rule="21" enabled="true"/>
        </reductions>
      </actions>
      <solved-conflicts/>
    </state>

    <state number="62">
      <itemset>
        <item rule-number="22" dot="3"/>
      </itemset>
      <actions>
        <transitions>
          <transition type="shift" symbol="NUMBER" state="83"/>
        </transitions>
        <errors/>
        <reductions/>
      </actions>
      <solved-conflicts/>
    </state>

    <state number="63">
      <itemset>
        <item rule-number="28" dot="3"/>
        <item rule-number="35" dot="1"/>
        <item rule-number="36" dot="1"/>
        <item rule-number="37" dot="1"/>
      </itemset>
      <actions>
        <transitions>
          <transition type="shift" symbol="SEMICOLON" state="84"/>
          <transition type="shift" symbol="PLUS" state="53"/>
          <transition type="shift" symbol="MULT" state="54"/>
        </transitions>
        <errors/>
        <reductions/>
      </actions>
      <solved-conflicts/>
    </state>

    <state number="64">
      <itemset>
        <item rule-number="33" dot="0"/>
        <item rule-number="34" dot="0"/>
        <item rule-number="35" dot="0"/>
        <item rule-number="36" dot="0"/>
        <item rule-number="37" dot="0"/>
        <item rule-number="38" dot="0"/>
        <item rule-number="39" dot="0"/>
        <item rule-number="40" dot="0"/>
        <item rule-number="41" dot="0"/>
        <item rule-number="42" dot="0"/>
        <item rule-number="43" dot="0"/>
        <item rule-number="46" dot="0"/>
        <item rule-number="47" dot="0"/>
        <item rule-number="48" dot="0"/>
        <item rule-number="49" dot="0"/>
        <item rule-number="50" dot="0">
          <lookaheads>
            <symbol>RPAR</symbol>
          </lookaheads>
        </item>
        <item rule-number="51" dot="0"/>
        <item rule-number="52" dot="0"/>
        <item rule-number="52" dot="2"/>
      </itemset>
      <actions>
        <transitions>
          <transition type="shift" symbol="ID" state="40"/>
          <transition type="shift" symbol="NUMBER" state="26"/>
          <transition type="goto" symbol="Expr" state="49"/>
          <transition type="goto" symbol="Primary" state="42"/>
          <transition type="goto" symbol="ExprList" state="85"/>
        </transitions>
        <errors/>
        <reductions>
          <reduction symbol="$default" rule="50" enabled="true"/>
        </reductions>
      </actions>
      <solved-conflicts/>
    </state>

    <state number="65">
      <itemset>
        <item rule-number="48" dot="4"/>
      </itemset>
      <actions>
        <transitions/>
        <errors/>
        <reductions>
          <reduction symbol="$default" rule="48" enabled="true"/>
        </reductions>
      </actions>
      <solved-conflicts/>
    </state>

    <state number="66">
      <itemset>
        <item rule-number="49" dot="4"/>
      </itemset>
      <actions>
        <transitions/>
        <errors/>
        <reductions>
          <reduction symbol="$default" rule="49" enabled="true"/>
        </reductions>
      </actions>
      <solved-conflicts/>
    </state>

    <state number="67">
      <itemset>
        <item rule-number="35" dot="1"/>
        <item rule-number="36" dot="1"/>
        <item rule-number="37" dot="1"/>
        <item rule-number="37" dot="3">
          <lookaheads>
            <symbol>SEMICOLON</symbol>
            <symbol>COMMA</symbol>
            <symbol>PLUS</symbol>
            <symbol>RPAR</symbol>
            <symbol>LESSTHN</symbol>
            <symbol>GRTRTHN</symbol>
            <symbol>LESSTHNEQ</symbol>
            <symbol>GRTRTHNEQ</symbol>
            <symbol>EQEQ</symbol>
            <symbol>NOTEQ</symbol>
          </lookaheads>
        </item>
      </itemset>
      <actions>
        <transitions>
          <transition type="shift" symbol="MULT" state="54"/>
        </transitions>
        <errors/>
        <reductions>
          <reduction symbol="$default" rule="37" enabled="true"/>
        </reductions>
      </actions>
      <solved-conflicts>
        <resolution rule="37" symbol="PLUS" type="reduce">%left PLUS</resolution>
        <resolution rule="37" symbol="MULT" type="shift">PLUS &lt; MULT</resolution>
      </solved-conflicts>
    </state>

    <state number="68">
      <itemset>
        <item rule-number="35" dot="1"/>
        <item rule-number="35" dot="3">
          <lookaheads>
            <symbol>SEMICOLON</symbol>
            <symbol>COMMA</symbol>
            <symbol>PLUS</symbol>
            <symbol>MULT</symbol>
            <symbol>RPAR</symbol>
            <symbol>LESSTHN</symbol>
            <symbol>GRTRTHN</symbol>
            <symbol>LESSTHNEQ</symbol>
            <symbol>GRTRTHNEQ</symbol>
            <symbol>EQEQ</symbol>
            <symbol>NOTEQ</symbol>
          </lookaheads>
        </item>
        <item rule-number="36" dot="1"/>
        <item rule-number="37" dot="1"/>
      </itemset>
      <actions>
        <transitions/>
        <errors/>
        <reductions>
          <reduction symbol="$default" rule="35" enabled="true"/>
        </reductions>
      </actions>
      <solved-conflicts>
        <resolution rule="35" symbol="PLUS" type="reduce">PLUS &lt; MULT</resolution>
        <resolution rule="35" symbol="MULT" type="reduce">%left MULT</resolution>
      </solved-conflicts>
    </state>

    <state number="69">
      <itemset>
        <item rule-number="33" dot="1">
          <lookaheads>
            <symbol>SEMICOLON</symbol>
            <symbol>COMMA</symbol>
            <symbol>PLUS</symbol>
            <symbol>MULT</symbol>
            <symbol>RPAR</symbol>
            <symbol>LESSTHN</symbol>
            <symbol>GRTRTHN</symbol>
            <symbol>LESSTHNEQ</symbol>
            <symbol>GRTRTHNEQ</symbol>
            <symbol>EQEQ</symbol>
            <symbol>NOTEQ</symbol>
          </lookaheads>
        </item>
        <item rule-number="36" dot="3">
          <lookaheads>
            <symbol>SEMICOLON</symbol>
            <symbol>COMMA</symbol>
            <symbol>PLUS</symbol>
            <symbol>MULT</symbol>
            <symbol>RPAR</symbol>
            <symbol>LESSTHN</symbol>
            <symbol>GRTRTHN</symbol>
            <symbol>LESSTHNEQ</symbol>
            <symbol>GRTRTHNEQ</symbol>
            <symbol>EQEQ</symbol>
            <symbol>NOTEQ</symbol>
          </lookaheads>
        </item>
        <item rule-number="38" dot="1"/>
        <item rule-number="39" dot="1"/>
        <item rule-number="40" dot="1"/>
        <item rule-number="41" dot="1"/>
        <item rule-number="42" dot="1"/>
        <item rule-number="43" dot="1"/>
      </itemset>
      <actions>
        <transitions>
          <transition type="shift" symbol="MINUS" state="56"/>
          <transition type="shift" symbol="DIV" state="57"/>
        </transitions>
        <errors/>
        <reductions>
          <reduction symbol="SEMICOLON" rule="33" enabled="true"/>
          <reduction symbol="SEMICOLON" rule="36" enabled="false"/>
          <reduction symbol="COMMA" rule="33" enabled="true"/>
          <reduction symbol="COMMA" rule="36" enabled="false"/>
          <reduction symbol="PLUS" rule="33" enabled="true"/>
          <reduction symbol="PLUS" rule="36" enabled="false"/>
          <reduction symbol="MULT" rule="33" enabled="true"/>
          <reduction symbol="MULT" rule="36" enabled="false"/>
          <reduction symbol="RPAR" rule="33" enabled="true"/>
          <reduction symbol="RPAR" rule="36" enabled="false"/>
          <reduction symbol="LESSTHN" rule="33" enabled="true"/>
          <reduction symbol="LESSTHN" rule="36" enabled="false"/>
          <reduction symbol="GRTRTHN" rule="33" enabled="true"/>
          <reduction symbol="GRTRTHN" rule="36" enabled="false"/>
          <reduction symbol="LESSTHNEQ" rule="33" enabled="true"/>
          <reduction symbol="LESSTHNEQ" rule="36" enabled="false"/>
          <reduction symbol="GRTRTHNEQ" rule="33" enabled="true"/>
          <reduction symbol="GRTRTHNEQ" rule="36" enabled="false"/>
          <reduction symbol="EQEQ" rule="33" enabled="true"/>
          <reduction symbol="EQEQ" rule="36" enabled="false"/>
          <reduction symbol="NOTEQ" rule="33" enabled="true"/>
          <reduction symbol="NOTEQ" rule="36" enabled="false"/>
          <reduction symbol="$default" rule="33" enabled="true"/>
        </reductions>
      </actions>
      <solved-conflicts>
        <resolution rule="36" symbol="PLUS" type="reduce">PLUS &lt; MULT</resolution>
      </solved-conflicts>
    </state>

    <state number="70">
      <itemset>
        <item rule-number="35" dot="1"/>
        <item rule-number="36" dot="1"/>
        <item rule-number="37" dot="1"/>
        <item rule-number="38" dot="3">
          <lookaheads>
            <symbol>SEMICOLON</symbol>
            <symbol>COMMA</symbol>
            <symbol>PLUS</symbol>
            <symbol>RPAR</symbol>
            <symbol>LESSTHN</symbol>
            <symbol>GRTRTHN</symbol>
            <symbol>LESSTHNEQ</symbol>
            <symbol>GRTRTHNEQ</symbol>
            <symbol>EQEQ</symbol>
            <symbol>NOTEQ</symbol>
          </lookaheads>
        </item>
      </itemset>
      <actions>
        <transitions>
          <transition type="shift" symbol="MULT" state="54"/>
        </transitions>
        <errors/>
        <reductions>
          <reduction symbol="$default" rule="38" enabled="true"/>
        </reductions>
      </actions>
      <solved-conflicts>
        <resolution rule="38" symbol="PLUS" type="reduce">%left PLUS</resolution>
        <resolution rule="38" symbol="MULT" type="shift">PLUS &lt; MULT</resolution>
      </solved-conflicts>
    </state>

    <state number="71">
      <itemset>
        <item rule-number="33" dot="1">
          <lookaheads>
            <symbol>SEMICOLON</symbol>
            <symbol>COMMA</symbol>
            <symbol>PLUS</symbol>
            <symbol>MULT</symbol>
            <symbol>RPAR</symbol>
            <symbol>LESSTHN</symbol>
            <symbol>GRTRTHN</symbol>
            <symbol>LESSTHNEQ</symbol>
            <symbol>GRTRTHNEQ</symbol>
            <symbol>EQEQ</symbol>
            <symbol>NOTEQ</symbol>
          </lookaheads>
        </item>
        <item rule-number="38" dot="1"/>
        <item rule-number="39" dot="1"/>
        <item rule-number="39" dot="3">
          <lookaheads>
            <symbol>SEMICOLON</symbol>
            <symbol>COMMA</symbol>
            <symbol>PLUS</symbol>
            <symbol>MULT</symbol>
            <symbol>RPAR</symbol>
            <symbol>LESSTHN</symbol>
            <symbol>GRTRTHN</symbol>
            <symbol>LESSTHNEQ</symbol>
            <symbol>GRTRTHNEQ</symbol>
            <symbol>EQEQ</symbol>
            <symbol>NOTEQ</symbol>
          </lookaheads>
        </item>
        <item rule-number="40" dot="1"/>
        <item rule-number="41" dot="1"/>
        <item rule-number="42" dot="1"/>
        <item rule-number="43" dot="1"/>
      </itemset>
      <actions>
        <transitions>
          <transition type="shift" symbol="MINUS" state="56"/>
          <transition type="shift" symbol="DIV" state="57"/>
        </transitions>
        <errors/>
        <reductions>
          <reduction symbol="SEMICOLON" rule="33" enabled="true"/>
          <reduction symbol="SEMICOLON" rule="39" enabled="false"/>
          <reduction symbol="COMMA" rule="33" enabled="true"/>
          <reduction symbol="COMMA" rule="39" enabled="false"/>
          <reduction symbol="PLUS" rule="33" enabled="true"/>
          <reduction symbol="PLUS" rule="39" enabled="false"/>
          <reduction symbol="MULT" rule="33" enabled="true"/>
          <reduction symbol="MULT" rule="39" enabled="false"/>
          <reduction symbol="RPAR" rule="33" enabled="true"/>
          <reduction symbol="RPAR" rule="39" enabled="false"/>
          <reduction symbol="LESSTHN" rule="33" enabled="true"/>
          <reduction symbol="LESSTHN" rule="39" enabled="false"/>
          <reduction symbol="GRTRTHN" rule="33" enabled="true"/>
          <reduction symbol="GRTRTHN" rule="39" enabled="false"/>
          <reduction symbol="LESSTHNEQ" rule="33" enabled="true"/>
          <reduction symbol="LESSTHNEQ" rule="39" enabled="false"/>
          <reduction symbol="GRTRTHNEQ" rule="33" enabled="true"/>
          <reduction symbol="GRTRTHNEQ" rule="39" enabled="false"/>
          <reduction symbol="EQEQ" rule="33" enabled="true"/>
          <reduction symbol="EQEQ" rule="39" enabled="false"/>
          <reduction symbol="NOTEQ" rule="33" enabled="true"/>
          <reduction symbol="NOTEQ" rule="39" enabled="false"/>
          <reduction symbol="$default" rule="33" enabled="true"/>
        </reductions>
      </actions>
      <solved-conflicts>
        <resolution rule="39" symbol="PLUS" type="reduce">%left PLUS</resolution>
      </solved-conflicts>
    </state>

    <state number="72">
      <itemset>
        <item rule-number="35" dot="1"/>
        <item rule-number="36" dot="1"/>
        <item rule-number="37" dot="1"/>
        <item rule-number="42" dot="3">
          <lookaheads>
            <symbol>SEMICOLON</symbol>
            <symbol>COMMA</symbol>
            <symbol>PLUS</symbol>
            <symbol>RPAR</symbol>
            <symbol>LESSTHN</symbol>
            <symbol>GRTRTHN</symbol>
            <symbol>LESSTHNEQ</symbol>
            <symbol>GRTRTHNEQ</symbol>
            <symbol>EQEQ</symbol>
            <symbol>NOTEQ</symbol>
          </lookaheads>
        </item>
      </itemset>
      <actions>
        <transitions>
          <transition type="shift" symbol="MULT" state="54"/>
        </transitions>
        <errors/>
        <reductions>
          <reduction symbol="$default" rule="42" enabled="true"/>
        </reductions>
      </actions>
      <solved-conflicts>
        <resolution rule="42" symbol="PLUS" type="reduce">%left PLUS</resolution>
        <resolution rule="42" symbol="MULT" type="shift">MINUS &lt; MULT</resolution>
      </solved-conflicts>
    </state>

    <state number="73">
      <itemset>
        <item rule-number="33" dot="1">
          <lookaheads>
            <symbol>SEMICOLON</symbol>
            <symbol>COMMA</symbol>
            <symbol>PLUS</symbol>
            <symbol>MULT</symbol>
            <symbol>RPAR</symbol>
            <symbol>LESSTHN</symbol>
            <symbol>GRTRTHN</symbol>
            <symbol>LESSTHNEQ</symbol>
            <symbol>GRTRTHNEQ</symbol>
            <symbol>EQEQ</symbol>
            <symbol>NOTEQ</symbol>
          </lookaheads>
        </item>
        <item rule-number="38" dot="1"/>
        <item rule-number="39" dot="1"/>
        <item rule-number="40" dot="1"/>
        <item rule-number="41" dot="1"/>
        <item rule-number="42" dot="1"/>
        <item rule-number="43" dot="1"/>
        <item rule-number="43" dot="3">
          <lookaheads>
            <symbol>SEMICOLON</symbol>
            <symbol>COMMA</symbol>
            <symbol>PLUS</symbol>
            <symbol>MULT</symbol>
            <symbol>RPAR</symbol>
            <symbol>LESSTHN</symbol>
            <symbol>GRTRTHN</symbol>
            <symbol>LESSTHNEQ</symbol>
            <symbol>GRTRTHNEQ</symbol>
            <symbol>EQEQ</symbol>
            <symbol>NOTEQ</symbol>
          </lookaheads>
        </item>
      </itemset>
      <actions>
        <transitions>
          <transition type="shift" symbol="MINUS" state="56"/>
          <transition type="shift" symbol="DIV" state="57"/>
        </transitions>
        <errors/>
        <reductions>
          <reduction symbol="SEMICOLON" rule="33" enabled="true"/>
          <reduction symbol="SEMICOLON" rule="43" enabled="false"/>
          <reduction symbol="COMMA" rule="33" enabled="true"/>
          <reduction symbol="COMMA" rule="43" enabled="false"/>
          <reduction symbol="PLUS" rule="33" enabled="true"/>
          <reduction symbol="PLUS" rule="43" enabled="false"/>
          <reduction symbol="MULT" rule="33" enabled="true"/>
          <reduction symbol="MULT" rule="43" enabled="false"/>
          <reduction symbol="RPAR" rule="33" enabled="true"/>
          <reduction symbol="RPAR" rule="43" enabled="false"/>
          <reduction symbol="LESSTHN" rule="33" enabled="true"/>
          <reduction symbol="LESSTHN" rule="43" enabled="false"/>
          <reduction symbol="GRTRTHN" rule="33" enabled="true"/>
          <reduction symbol="GRTRTHN" rule="43" enabled="false"/>
          <reduction symbol="LESSTHNEQ" rule="33" enabled="true"/>
          <reduction symbol="LESSTHNEQ" rule="43" enabled="false"/>
          <reduction symbol="GRTRTHNEQ" rule="33" enabled="true"/>
          <reduction symbol="GRTRTHNEQ" rule="43" enabled="false"/>
          <reduction symbol="EQEQ" rule="33" enabled="true"/>
          <reduction symbol="EQEQ" rule="43" enabled="false"/>
          <reduction symbol="NOTEQ" rule="33" enabled="true"/>
          <reduction symbol="NOTEQ" rule="43" enabled="false"/>
          <reduction symbol="$default" rule="33" enabled="true"/>
        </reductions>
      </actions>
      <solved-conflicts>
        <resolution rule="43" symbol="PLUS" type="reduce">%left PLUS</resolution>
      </solved-conflicts>
    </state>

    <state number="74">
      <itemset>
        <item rule-number="35" dot="1"/>
        <item rule-number="36" dot="1"/>
        <item rule-number="37" dot="1"/>
        <item rule-number="40" dot="3">
          <lookaheads>
            <symbol>SEMICOLON</symbol>
            <symbol>COMMA</symbol>
            <symbol>PLUS</symbol>
            <symbol>MULT</symbol>
            <symbol>RPAR</symbol>
            <symbol>LESSTHN</symbol>
            <symbol>GRTRTHN</symbol>
            <symbol>LESSTHNEQ</symbol>
            <symbol>GRTRTHNEQ</symbol>
            <symbol>EQEQ</symbol>
            <symbol>NOTEQ</symbol>
          </lookaheads>
        </item>
      </itemset>
      <actions>
        <transitions/>
        <errors/>
        <reductions>
          <reduction symbol="$default" rule="40" enabled="true"/>
        </reductions>
      </actions>
      <solved-conflicts>
        <resolution rule="40" symbol="PLUS" type="reduce">PLUS &lt; DIV</resolution>
        <resolution rule="40" symbol="MULT" type="reduce">%left MULT</resolution>
      </solved-conflicts>
    </state>

    <state number="75">
      <itemset>
        <item rule-number="33" dot="1">
          <lookaheads>
            <symbol>SEMICOLON</symbol>
            <symbol>COMMA</symbol>
            <symbol>PLUS</symbol>
            <symbol>MULT</symbol>
            <symbol>RPAR</symbol>
            <symbol>LESSTHN</symbol>
            <symbol>GRTRTHN</symbol>
            <symbol>LESSTHNEQ</symbol>
            <symbol>GRTRTHNEQ</symbol>
            <symbol>EQEQ</symbol>
            <symbol>NOTEQ</symbol>
          </lookaheads>
        </item>
        <item rule-number="38" dot="1"/>
        <item rule-number="39" dot="1"/>
        <item rule-number="40" dot="1"/>
        <item rule-number="41" dot="1"/>
        <item rule-number="41" dot="3">
          <lookaheads>
            <symbol>SEMICOLON</symbol>
            <symbol>COMMA</symbol>
            <symbol>PLUS</symbol>
            <symbol>MULT</symbol>
            <symbol>RPAR</symbol>
            <symbol>LESSTHN</symbol>
            <symbol>GRTRTHN</symbol>
            <symbol>LESSTHNEQ</symbol>
            <symbol>GRTRTHNEQ</symbol>
            <symbol>EQEQ</symbol>
            <symbol>NOTEQ</symbol>
          </lookaheads>
        </item>
        <item rule-number="42" dot="1"/>
        <item rule-number="43" dot="1"/>
      </itemset>
      <actions>
        <transitions>
          <transition type="shift" symbol="MINUS" state="56"/>
          <transition type="shift" symbol="DIV" state="57"/>
        </transitions>
        <errors/>
        <reductions>
          <reduction symbol="SEMICOLON" rule="33" enabled="true"/>
          <reduction symbol="SEMICOLON" rule="41" enabled="false"/>
          <reduction symbol="COMMA" rule="33" enabled="true"/>
          <reduction symbol="COMMA" rule="41" enabled="false"/>
          <reduction symbol="PLUS" rule="33" enabled="true"/>
          <reduction symbol="PLUS" rule="41" enabled="false"/>
          <reduction symbol="MULT" rule="33" enabled="true"/>
          <reduction symbol="MULT" rule="41" enabled="false"/>
          <reduction symbol="RPAR" rule="33" enabled="true"/>
          <reduction symbol="RPAR" rule="41" enabled="false"/>
          <reduction symbol="LESSTHN" rule="33" enabled="true"/>
          <reduction symbol="LESSTHN" rule="41" enabled="false"/>
          <reduction symbol="GRTRTHN" rule="33" enabled="true"/>
          <reduction symbol="GRTRTHN" rule="41" enabled="false"/>
          <reduction symbol="LESSTHNEQ" rule="33" enabled="true"/>
          <reduction symbol="LESSTHNEQ" rule="41" enabled="false"/>
          <reduction symbol="GRTRTHNEQ" rule="33" enabled="true"/>
          <reduction symbol="GRTRTHNEQ" rule="41" enabled="false"/>
          <reduction symbol="EQEQ" rule="33" enabled="true"/>
          <reduction symbol="EQEQ" rule="41" enabled="false"/>
          <reduction symbol="NOTEQ" rule="33" enabled="true"/>
          <reduction symbol="NOTEQ" rule="41" enabled="false"/>
          <reduction symbol="$default" rule="33" enabled="true"/>
        </reductions>
      </actions>
      <solved-conflicts>
        <resolution rule="41" symbol="PLUS" type="reduce">PLUS &lt; DIV</resolution>
      </solved-conflicts>
    </state>

    <state number="76">
      <itemset>
        <item rule-number="9" dot="0"/>
        <item rule-number="32" dot="4"/>
        <item rule-number="44" dot="0"/>
        <item rule-number="45" dot="0"/>
      </itemset>
      <actions>
        <transitions>
          <transition type="shift" symbol="LCBRA" state="18"/>
          <transition type="goto" symbol="Block" state="86"/>
          <transition type="goto" symbol="IfBlock" state="87"/>
        </transitions>
        <errors/>
        <reductions/>
      </actions>
      <solved-conflicts/>
    </state>

    <state number="77">
      <itemset>
        <item rule-number="10" dot="2"/>
        <item rule-number="33" dot="0"/>
        <item rule-number="34" dot="0"/>
        <item rule-number="35" dot="0"/>
        <item rule-number="36" dot="0"/>
        <item rule-number="37" dot="0"/>
        <item rule-number="38" dot="0"/>
        <item rule-number="39" dot="0"/>
        <item rule-number="40" dot="0"/>
        <item rule-number="41" dot="0"/>
        <item rule-number="42" dot="0"/>
        <item rule-number="43" dot="0"/>
        <item rule-number="46" dot="0"/>
        <item rule-number="47" dot="0"/>
        <item rule-number="48" dot="0"/>
        <item rule-number="49" dot="0"/>
      </itemset>
      <actions>
        <transitions>
          <transition type="shift" symbol="ID" state="40"/>
          <transition type="shift" symbol="NUMBER" state="26"/>
          <transition type="goto" symbol="Expr" state="88"/>
          <transition type="goto" symbol="Primary" state="42"/>
        </transitions>
        <errors/>
        <reductions/>
      </actions>
      <solved-conflicts/>
    </state>

    <state number="78">
      <itemset>
        <item rule-number="11" dot="2"/>
        <item rule-number="33" dot="0"/>
        <item rule-number="34" dot="0"/>
        <item rule-number="35" dot="0"/>
        <item rule-number="36" dot="0"/>
        <item rule-number="37" dot="0"/>
        <item rule-number="38" dot="0"/>
        <item rule-number="39" dot="0"/>
        <item rule-number="40" dot="0"/>
        <item rule-number="41" dot="0"/>
        <item rule-number="42" dot="0"/>
        <item rule-number="43" dot="0"/>
        <item rule-number="46" dot="0"/>
        <item rule-number="47" dot="0"/>
        <item rule-number="48" dot="0"/>
        <item rule-number="49" dot="0"/>
      </itemset>
      <actions>
        <transitions>
          <transition type="shift" symbol="ID" state="40"/>
          <transition type="shift" symbol="NUMBER" state="26"/>
          <transition type="goto" symbol="Expr" state="89"/>
          <transition type="goto" symbol="Primary" state="42"/>
        </transitions>
        <errors/>
        <reductions/>
      </actions>
      <solved-conflicts/>
    </state>

    <state number="79">
      <itemset>
        <item rule-number="12" dot="2"/>
        <item rule-number="33" dot="0"/>
        <item rule-number="34" dot="0"/>
        <item rule-number="35" dot="0"/>
        <item rule-number="36" dot="0"/>
        <item rule-number="37" dot="0"/>
        <item rule-number="38" dot="0"/>
        <item rule-number="39" dot="0"/>
        <item rule-number="40" dot="0"/>
        <item rule-number="41" dot="0"/>
        <item rule-number="42" dot="0"/>
        <item rule-number="43" dot="0"/>
        <item rule-number="46" dot="0"/>
        <item rule-number="47" dot="0"/>
        <item rule-number="48" dot="0"/>
        <item rule-number="49" dot="0"/>
      </itemset>
      <actions>
        <transitions>
          <transition type="shift" symbol="ID" state="40"/>
          <transition type="shift" symbol="NUMBER" state="26"/>
          <transition type="goto" symbol="Expr" state="90"/>
          <transition type="goto" symbol="Primary" state="42"/>
        </transitions>
        <errors/>
        <reductions/>
      </actions>
      <solved-conflicts/>
    </state>

    <state number="80">
      <itemset>
        <item rule-number="13" dot="2"/>
        <item rule-number="33" dot="0"/>
        <item rule-number="34" dot="0"/>
        <item rule-number="35" dot="0"/>
        <item rule-number="36" dot="0"/>
        <item rule-number="37" dot="0"/>
        <item rule-number="38" dot="0"/>
        <item rule-number="39" dot="0"/>
        <item rule-number="40" dot="0"/>
        <item rule-number="41" dot="0"/>
        <item rule-number="42" dot="0"/>
        <item rule-number="43" dot="0"/>
        <item rule-number="46" dot="0"/>
        <item rule-number="47" dot="0"/>
        <item rule-number="48" dot="0"/>
        <item rule-number="49" dot="0"/>
      </itemset>
      <actions>
        <transitions>
          <transition type="shift" symbol="ID" state="40"/>
          <transition type="shift" symbol="NUMBER" state="26"/>
          <transition type="goto" symbol="Expr" state="91"/>
          <transition type="goto" symbol="Primary" state="42"/>
        </transitions>
        <errors/>
        <reductions/>
      </actions>
      <solved-conflicts/>
    </state>

    <state number="81">
      <itemset>
        <item rule-number="14" dot="2"/>
        <item rule-number="33" dot="0"/>
        <item rule-number="34" dot="0"/>
        <item rule-number="35" dot="0"/>
        <item rule-number="36" dot="0"/>
        <item rule-number="37" dot="0"/>
        <item rule-number="38" dot="0"/>
        <item rule-number="39" dot="0"/>
        <item rule-number="40" dot="0"/>
        <item rule-number="41" dot="0"/>
        <item rule-number="42" dot="0"/>
        <item rule-number="43" dot="0"/>
        <item rule-number="46" dot="0"/>
        <item rule-number="47" dot="0"/>
        <item rule-number="48" dot="0"/>
        <item rule-number="49" dot="0"/>
      </itemset>
      <actions>
        <transitions>
          <transition type="shift" symbol="ID" state="40"/>
          <transition type="shift" symbol="NUMBER" state="26"/>
          <transition type="goto" symbol="Expr" state="92"/>
          <transition type="goto" symbol="Primary" state="42"/>
        </transitions>
        <errors/>
        <reductions/>
      </actions>
      <solved-conflicts/>
    </state>

    <state number="82">
      <itemset>
        <item rule-number="15" dot="2"/>
        <item rule-number="33" dot="0"/>
        <item rule-number="34" dot="0"/>
        <item rule-number="35" dot="0"/>
        <item rule-number="36" dot="0"/>
        <item rule-number="37" dot="0"/>
        <item rule-number="38" dot="0"/>
        <item rule-number="39" dot="0"/>
        <item rule-number="40" dot="0"/>
        <item rule-number="41" dot="0"/>
        <item rule-number="42" dot="0"/>
        <item rule-number="43" dot="0"/>
        <item rule-number="46" dot="0"/>
        <item rule-number="47" dot="0"/>
        <item rule-number="48" dot="0"/>
        <item rule-number="49" dot="0"/>
      </itemset>
      <actions>
        <transitions>
          <transition type="shift" symbol="ID" state="40"/>
          <transition type="shift" symbol="NUMBER" state="26"/>
          <transition type="goto" symbol="Expr" state="93"/>
          <transition type="goto" symbol="Primary" state="42"/>
        </transitions>
        <errors/>
        <reductions/>
      </actions>
      <solved-conflicts/>
    </state>

    <state number="83">
      <itemset>
        <item rule-number="22" dot="4"/>
      </itemset>
      <actions>
        <transitions>
          <transition type="shift" symbol="RBRA" state="94"/>
        </transitions>
        <errors/>
        <reductions/>
      </actions>
      <solved-conflicts/>
    </state>

    <state number="84">
      <itemset>
        <item rule-number="28" dot="4"/>
      </itemset>
      <actions>
        <transitions/>
        <errors/>
        <reductions>
          <reduction symbol="$default" rule="28" enabled="true"/>
        </reductions>
      </actions>
      <solved-conflicts/>
    </state>

    <state number="85">
      <itemset>
        <item rule-number="52" dot="3"/>
      </itemset>
      <actions>
        <transitions/>
        <errors/>
        <reductions>
          <reduction symbol="$default" rule="52" enabled="true"/>
        </reductions>
      </actions>
      <solved-conflicts/>
    </state>

    <state number="86">
      <itemset>
        <item rule-number="44" dot="1">
          <lookaheads>
            <symbol>CHAR</symbol>
            <symbol>INT</symbol>
            <symbol>ID</symbol>
            <symbol>SEMICOLON</symbol>
            <symbol>NUMBER</symbol>
            <symbol>WRITE</symbol>
            <symbol>WRITELN</symbol>
            <symbol>RETURN</symbol>
            <symbol>IF</symbol>
            <symbol>RCBRA</symbol>
          </lookaheads>
        </item>
        <item rule-number="45" dot="1"/>
      </itemset>
      <actions>
        <transitions>
          <transition type="shift" symbol="ELSE" state="95"/>
        </transitions>
        <errors/>
        <reductions>
          <reduction symbol="$default" rule="44" enabled="true"/>
        </reductions>
      </actions>
      <solved-conflicts/>
    </state>

    <state number="87">
      <itemset>
        <item rule-number="32" dot="5"/>
      </itemset>
      <actions>
        <transitions/>
        <errors/>
        <reductions>
          <reduction symbol="$default" rule="32" enabled="true"/>
        </reductions>
      </actions>
      <solved-conflicts/>
    </state>

    <state number="88">
      <itemset>
        <item rule-number="10" dot="3">
          <lookaheads>
            <symbol>RPAR</symbol>
          </lookaheads>
        </item>
        <item rule-number="35" dot="1"/>
        <item rule-number="36" dot="1"/>
        <item rule-number="37" dot="1"/>
      </itemset>
      <actions>
        <transitions>
          <transition type="shift" symbol="PLUS" state="53"/>
          <transition type="shift" symbol="MULT" state="54"/>
        </transitions>
        <errors/>
        <reductions>
          <reduction symbol="$default" rule="10" enabled="true"/>
        </reductions>
      </actions>
      <solved-conflicts/>
    </state>

    <state number="89">
      <itemset>
        <item rule-number="11" dot="3">
          <lookaheads>
            <symbol>RPAR</symbol>
          </lookaheads>
        </item>
        <item rule-number="35" dot="1"/>
        <item rule-number="36" dot="1"/>
        <item rule-number="37" dot="1"/>
      </itemset>
      <actions>
        <transitions>
          <transition type="shift" symbol="PLUS" state="53"/>
          <transition type="shift" symbol="MULT" state="54"/>
        </transitions>
        <errors/>
        <reductions>
          <reduction symbol="$default" rule="11" enabled="true"/>
        </reductions>
      </actions>
      <solved-conflicts/>
    </state>

    <state number="90">
      <itemset>
        <item rule-number="12" dot="3">
          <lookaheads>
            <symbol>RPAR</symbol>
          </lookaheads>
        </item>
        <item rule-number="35" dot="1"/>
        <item rule-number="36" dot="1"/>
        <item rule-number="37" dot="1"/>
      </itemset>
      <actions>
        <transitions>
          <transition type="shift" symbol="PLUS" state="53"/>
          <transition type="shift" symbol="MULT" state="54"/>
        </transitions>
        <errors/>
        <reductions>
          <reduction symbol="$default" rule="12" enabled="true"/>
        </reductions>
      </actions>
      <solved-conflicts/>
    </state>

    <state number="91">
      <itemset>
        <item rule-number="13" dot="3">
          <lookaheads>
            <symbol>RPAR</symbol>
          </lookaheads>
        </item>
        <item rule-number="35" dot="1"/>
        <item rule-number="36" dot="1"/>
        <item rule-number="37" dot="1"/>
      </itemset>
      <actions>
        <transitions>
          <transition type="shift" symbol="PLUS" state="53"/>
          <transition type="shift" symbol="MULT" state="54"/>
        </transitions>
        <errors/>
        <reductions>
          <reduction symbol="$default" rule="13" enabled="true"/>
        </reductions>
      </actions>
      <solved-conflicts/>
    </state>

    <state number="92">
      <itemset>
        <item rule-number="14" dot="3">
          <lookaheads>
            <symbol>RPAR</symbol>
          </lookaheads>
        </item>
        <item rule-number="35" dot="1"/>
        <item rule-number="36" dot="1"/>
        <item rule-number="37" dot="1"/>
      </itemset>
      <actions>
        <transitions>
          <transition type="shift" symbol="PLUS" state="53"/>
          <transition type="shift" symbol="MULT" state="54"/>
        </transitions>
        <errors/>
        <reductions>
          <reduction symbol="$default" rule="14" enabled="true"/>
        </reductions>
      </actions>
      <solved-conflicts/>
    </state>

    <state number="93">
      <itemset>
        <item rule-number="15" dot="3">
          <lookaheads>
            <symbol>RPAR</symbol>
          </lookaheads>
        </item>
        <item rule-number="35" dot="1"/>
        <item rule-number="36" dot="1"/>
        <item rule-number="37" dot="1"/>
      </itemset>
      <actions>
        <transitions>
          <transition type="shift" symbol="PLUS" state="53"/>
          <transition type="shift" symbol="MULT" state="54"/>
        </transitions>
        <errors/>
        <reductions>
          <reduction symbol="$default" rule="15" enabled="true"/>
        </reductions>
      </actions>
      <solved-conflicts/>
    </state>

    <state number="94">
      <itemset>
        <item rule-number="22" dot="5"/>
      </itemset>
      <actions>
        <transitions>
          <transition type="shift" symbol="SEMICOLON" state="96"/>
        </transitions>
        <errors/>
        <reductions/>
      </actions>
      <solved-conflicts/>
    </state>

    <state number="95">
      <itemset>
        <item rule-number="9" dot="0"/>
        <item rule-number="45" dot="2"/>
      </itemset>
      <actions>
        <transitions>
          <transition type="shift" symbol="LCBRA" state="18"/>
          <transition type="goto" symbol="Block" state="97"/>
        </transitions>
        <errors/>
        <reductions/>
      </actions>
      <solved-conflicts/>
    </state>

    <state number="96">
      <itemset>
        <item rule-number="22" dot="6"/>
      </itemset>
      <actions>
        <transitions/>
        <errors/>
        <reductions>
          <reduction symbol="$default" rule="22" enabled="true"/>
        </reductions>
      </actions>
      <solved-conflicts/>
    </state>

    <state number="97">
      <itemset>
        <item rule-number="45" dot="3"/>
      </itemset>
      <actions>
        <transitions/>
        <errors/>
        <reductions>
          <reduction symbol="$default" rule="45" enabled="true"/>
        </reductions>
      </actions>
      <solved-conflicts/>
    </state>
  </automaton>
</bison-xml-report>
